[{"_id":"D7ZC6","attn_check":false,"effort":"I tried my best on each question","difficulty":3,"confidence":3,"enjoyment":3,"other":"","age":"23","country":"China","language":"Mandarin","schoolyear":"Fourth","major":"Social Sciences (incl. CogSci)","gender":"Female","disability":"","subject":"D7ZC6","study":"SGC4C","condition":"113112","session":"su22sona","browser":"chrome","width":1339,"height":881,"os":"Mac OS","starttime":"2022-07-20T06:56:35.006Z","totaltime":334705,"violations":1,"absolute_score":1,"discriminant_score":-5,"tri_score":1,"orth_score":6,"other_score":12,"blank_score":0,"exp_id":"2218","sona_id":"42780","pool":"sona","mode":"asynch","status":"success"},{"_id":"CT1PY","attn_check":true,"effort":"I tried my best on each question","difficulty":4,"confidence":2,"enjoyment":3,"other":"","age":"19","country":"United States","language":"English","schoolyear":"Secondary School/Highschool","major":"Natural Sciences","gender":"Female","disability":"","subject":"CT1PY","study":"SGC4C","condition":"113112","session":"suPROLIFIC","browser":"chrome","width":1440,"height":821,"os":"Mac OS","starttime":"2022-07-20T06:18:17.696Z","totaltime":520398,"violations":2,"absolute_score":7,"discriminant_score":7.083333333333333,"tri_score":10,"orth_score":0,"other_score":5,"blank_score":2,"exp_id":"62d78f270296bdf7e6cf9515","sona_id":"62d59ab6f7d966eece474824","pool":"prolific","mode":"asynch","status":"success"},{"_id":"QOHN7","attn_check":true,"effort":"I tried my best on most questions","difficulty":4,"confidence":2,"enjoyment":1,"other":"","age":"32","country":"United States","language":"English","schoolyear":"Bachelors Degree","major":"Social Sciences (incl. CogSci)","gender":"Female","disability":"","subject":"QOHN7","study":"SGC4C","condition":"113112","session":"suPROLIFIC","browser":"chrome","width":1334,"height":1000,"os":"Mac OS","starttime":"2022-07-20T06:07:33.858Z","totaltime":739378,"violations":1,"absolute_score":8,"discriminant_score":3.916666666666667,"tri_score":11,"orth_score":4,"other_score":1,"blank_score":0,"exp_id":"62d78f270296bdf7e6cf9515","sona_id":"5e3a7e26ca5cf328020dc4b6","pool":"prolific","mode":"asynch","status":"success"},{"_id":"R0AON","attn_check":true,"effort":"I tried my best on each question","difficulty":3,"confidence":3,"enjoyment":4,"other":"The way the graphs were tilted made them hard to read.","age":"30","country":"USA","language":"English","schoolyear":"Graduate Degree","major":"Math or Computer Sciences","gender":"Female","disability":"no","subject":"R0AON","study":"SGC4C","condition":"113112","session":"suPROLIFIC","browser":"chrome","width":1280,"height":689,"os":"Mac OS","starttime":"2022-07-20T05:46:09.745Z","totaltime":928944,"violations":17.5,"absolute_score":9,"discriminant_score":11.333333333333332,"tri_score":14,"orth_score":0,"other_score":1,"blank_score":0,"exp_id":"62d78f270296bdf7e6cf9515","sona_id":"5d166d9e3727c40001915aa3","pool":"prolific","mode":"asynch","status":"success"},{"_id":"6AVLK","attn_check":true,"effort":"I tried my best on most questions","difficulty":4,"confidence":3,"enjoyment":3,"other":"","age":"23","country":"United States","language":"Cantonese","schoolyear":"Bachelors Degree","major":"Biomedical & Health Sciences","gender":"Female","disability":"","subject":"6AVLK","study":"SGC4C","condition":"113112","session":"suPROLIFIC","browser":"chrome","width":1440,"height":694,"os":"Mac OS","starttime":"2022-07-20T06:10:30.964Z","totaltime":757002,"violations":1,"absolute_score":9,"discriminant_score":10.75,"tri_score":14,"orth_score":0,"other_score":2,"blank_score":0,"exp_id":"62d78f270296bdf7e6cf9515","sona_id":"6100e620cb97cef5cc765920","pool":"prolific","mode":"asynch","status":"success"},{"_id":"QGBTT","attn_check":true,"effort":"I tried my best on each question","difficulty":4,"confidence":4,"enjoyment":2,"other":"I hated that the image was turned sideways so it was difficult to line up the numbers and letters as I had to tilt my head to view the image.","age":"18","country":"United States","language":"English","schoolyear":"Secondary School/Highschool","major":"Math or Computer Sciences","gender":"Male","disability":"I do not","subject":"QGBTT","study":"SGC4C","condition":"113112","session":"suPROLIFIC","browser":"chrome","width":1920,"height":937,"os":"Windows 10","starttime":"2022-07-20T05:22:10.421Z","totaltime":550627,"violations":1,"absolute_score":0,"discriminant_score":-11,"tri_score":1,"orth_score":15,"other_score":0,"blank_score":0,"exp_id":"62d78f270296bdf7e6cf9515","sona_id":"62d6d31b3e2a7f18a131c70c","pool":"prolific","mode":"asynch","status":"success"}]
